numeraicb.py
numeraicb-1.0.1.dist-info/DESCRIPTION.rst
numeraicb-1.0.1.dist-info/METADATA
numeraicb-1.0.1.dist-info/RECORD
numeraicb-1.0.1.dist-info/WHEEL
numeraicb-1.0.1.dist-info/metadata.json
numeraicb-1.0.1.dist-info/top_level.txt
