Metadata-Version: 2.0
Name: numeraicb
Version: 1.0.1
Summary: Keras Callback to track Numerai consistency
Home-page: https://github.com/volker48/numeraicb
Author: Marcus McCurdy
Author-email: marcus.mccurdy@gmail.com
License: MIT
Platform: UNKNOWN
Classifier: License :: OSI Approved :: MIT License
Classifier: Programming Language :: Python
Classifier: Programming Language :: Python :: 2.6
Classifier: Programming Language :: Python :: 2.7
Classifier: Programming Language :: Python :: 3
Classifier: Programming Language :: Python :: 3.3
Classifier: Programming Language :: Python :: 3.4
Classifier: Programming Language :: Python :: 3.5
Classifier: Programming Language :: Python :: 3.6
Classifier: Programming Language :: Python :: Implementation :: CPython
Classifier: Programming Language :: Python :: Implementation :: PyPy
Requires-Dist: Keras (>=2.0.0)
Requires-Dist: pandas (>=0.18.1)
Requires-Dist: numpy (>=1.9.1)
Requires-Dist: scikit-learn (>=0.18)
